task_processing/__init__.py
task_processing/metrics.py
task_processing/py.typed
task_processing/task_processor.py
task_processing/utils.py
task_processing/interfaces/__init__.py
task_processing/interfaces/event.py
task_processing/interfaces/persistence.py
task_processing/interfaces/runner.py
task_processing/interfaces/task_executor.py
task_processing/plugins/__init__.py
task_processing/plugins/kubernetes/__init__.py
task_processing/plugins/kubernetes/kube_client.py
task_processing/plugins/kubernetes/kubernetes_pod_executor.py
task_processing/plugins/kubernetes/task_config.py
task_processing/plugins/kubernetes/task_metadata.py
task_processing/plugins/kubernetes/types.py
task_processing/plugins/kubernetes/utils.py
task_processing/plugins/mesos/__init__.py
task_processing/plugins/mesos/constraints.py
task_processing/plugins/mesos/execution_framework.py
task_processing/plugins/mesos/logging_executor.py
task_processing/plugins/mesos/mesos_executor.py
task_processing/plugins/mesos/mesos_pod_executor.py
task_processing/plugins/mesos/mesos_task_executor.py
task_processing/plugins/mesos/metrics.py
task_processing/plugins/mesos/resource_helpers.py
task_processing/plugins/mesos/retrying_executor.py
task_processing/plugins/mesos/task_config.py
task_processing/plugins/mesos/timeout_executor.py
task_processing/plugins/mesos/translator.py
task_processing/plugins/persistence/__init__.py
task_processing/plugins/persistence/dynamodb_persistence.py
task_processing/plugins/persistence/file_persistence.py
task_processing/plugins/stateful/__init__.py
task_processing/plugins/stateful/stateful_executor.py
task_processing/runners/__init__.py
task_processing/runners/async_runner.py
task_processing/runners/promise.py
task_processing/runners/subscription.py
task_processing/runners/sync.py
task_processing-1.3.5.dist-info/LICENSE
task_processing-1.3.5.dist-info/METADATA
task_processing-1.3.5.dist-info/WHEEL
task_processing-1.3.5.dist-info/top_level.txt
task_processing-1.3.5.dist-info/RECORD
