Metadata-Version: 2.1
Name: task_processing
Version: 1.3.5
Summary: Framework for task processing executors and configuration
Author: Task Processing
Author-email: team-taskproc@yelp.com
Provides: task_processing
License-File: LICENSE
Requires-Dist: pyrsistent
Provides-Extra: k8s
Requires-Dist: kubernetes; extra == "k8s"
Requires-Dist: typing-extensions; extra == "k8s"
Provides-Extra: mesos_executor
Requires-Dist: addict; extra == "mesos-executor"
Requires-Dist: pymesos>=0.2.14; extra == "mesos-executor"
Requires-Dist: requests; extra == "mesos-executor"
Provides-Extra: metrics
Requires-Dist: yelp-meteorite; extra == "metrics"
Provides-Extra: persistence
Requires-Dist: boto3; extra == "persistence"
